flib/__init__.py
flib-0.9.2.dist-info/LICENSE
flib-0.9.2.dist-info/METADATA
flib-0.9.2.dist-info/WHEEL
flib-0.9.2.dist-info/top_level.txt
flib-0.9.2.dist-info/RECORD
