Metadata-Version: 2.1
Name: flib
Version: 0.9.2
Summary: Frootlab Shared Library
Home-page: https://www.frootlab.org/flib
Author: Frootlab Developers
Author-email: contact@frootlab.org
License: GPLv3
Keywords: library shared-library python-library
Platform: UNKNOWN
Classifier: Development Status :: 3 - Alpha
Classifier: Intended Audience :: Science/Research
Classifier: License :: OSI Approved :: GNU General Public License v3 (GPLv3)
Classifier: Programming Language :: Python :: 3
Classifier: Programming Language :: Python :: 3.7
Classifier: Operating System :: OS Independent
Classifier: Topic :: Software Development :: Libraries :: Python Modules
Requires-Python: >=3.7
Requires-Dist: appdirs (>=1.4.1)
Requires-Dist: pyparsing (>=2.2)
Provides-Extra: numpy
Requires-Dist: numpy (>=1.15) ; extra == 'numpy'
